LICENSE
MANIFEST.in
README.md
VERSION
setup.cfg
setup.py
nosql_rest_preprocessor/__init__.py
nosql_rest_preprocessor/exceptions.py
nosql_rest_preprocessor/models.py
nosql_rest_preprocessor/resolvers.py
nosql_rest_preprocessor/utils.py
nosql_rest_preprocessor.egg-info/PKG-INFO
nosql_rest_preprocessor.egg-info/SOURCES.txt
nosql_rest_preprocessor.egg-info/dependency_links.txt
nosql_rest_preprocessor.egg-info/top_level.txt