Metadata-Version: 1.1
Name: nosql-rest-preprocessor
Version: 0.3
Summary: A middleware module which solves common problems when building rest-apis with nosql databases.
Home-page: https://github.com/felixbr/nosql-rest-preprocessor/
Author: Felix Bruckmeier
Author-email: felix.m.bruckmeier@gmail.com
License: MIT
Download-URL: https://github.com/felixbr/nosql-rest-preprocessor/tarball/0.3
Keywords: nosql,rest,web,middleware
Platform: UNKNOWN
